
{
    "name": {
	    "select":true,
	    	"aka":false,
	    	"part":true,
	    	"full":false
    },

    "phone": {
	    "select":true,
	    	"total":true,
	    	"slice_len":{
		    "select":true,
		    "min":3,
		    "max":3
	    }
    },

    "place":{
        "select":false,
		"aka":false,
	    	"part":true,
	    	"full":false

    },


    "addr":{
        "select":false,
		"aka":false,
	    	"part":true,
	    	"full":false

    },


    "door":{
        "select":false,
		"aka":false,
	    	"part":true,
	    	"full":false

    },


    "birth":{
	"select":true,

        "separat":{
            "Y":true,
            "M":true,
            "D":true
        },

	"combin":{
		"Y_M":false,
            	"M_D":false,
            	"Y_M_D":false
	    }
    },

    "mail": {
        "select":false,
        "name":false,
        "domain":false
    },

    "slang":{
        "select":false,
        	"aka":false,
		"part":true,
		"full":false

    },


    "random":{
        "select":false,
	    "len":{
		    "min":3,
		    "max":3
	    }

    },


    "other":{
        "select":false
    },

    "extra_dic":{
        "select":false
    },

    "total_len":{
	    "select":false,
	    "range":{
		    "max":20,
		    "min":6
	    }
    }
}


